cfsiv_utils/WebScraping.py
cfsiv_utils/__init__.py
cfsiv_utils/data2csv.py
cfsiv_utils/filehandling.py
cfsiv_utils/log_handling.py
cfsiv_utils/time_strings.py
utils/WebScraping.py
utils/__init__.py
utils/data2csv.py
utils/filehandling.py
utils/time_strings.py
CFSIV_utils_Conradical-0.1.2.dist-info/LICENSE
CFSIV_utils_Conradical-0.1.2.dist-info/METADATA
CFSIV_utils_Conradical-0.1.2.dist-info/WHEEL
CFSIV_utils_Conradical-0.1.2.dist-info/top_level.txt
CFSIV_utils_Conradical-0.1.2.dist-info/RECORD
