Metadata-Version: 2.1
Name: CFSIV-utils-Conradical
Version: 0.1.2
Summary: A collection of Logging, Time, Date, Filehandling and webscraping functions
Home-page: https://github.com/conradstorz/utilities.git
Author: Conrad Storz IV
Author-email: conradstorz@gmail.com
License: UNKNOWN
Platform: UNKNOWN
Classifier: Programming Language :: Python :: 3
Classifier: License :: OSI Approved :: MIT License
Classifier: Operating System :: OS Independent
Requires-Python: >=3.8
